jwt_rsa/__init__.py
jwt_rsa/cli.py
jwt_rsa/convert.py
jwt_rsa/issue.py
jwt_rsa/jwks.py
jwt_rsa/key_tester.py
jwt_rsa/keygen.py
jwt_rsa/pubkey.py
jwt_rsa/py.typed
jwt_rsa/rsa.py
jwt_rsa/token.py
jwt_rsa/types.py
jwt_rsa/verify.py
pyjwt_rsa-1.2.0.dist-info/LICENCE
pyjwt_rsa-1.2.0.dist-info/METADATA
pyjwt_rsa-1.2.0.dist-info/WHEEL
pyjwt_rsa-1.2.0.dist-info/entry_points.txt
pyjwt_rsa-1.2.0.dist-info/RECORD
