Metadata-Version: 2.3
Name: pyjwt-rsa
Version: 1.2.0
Summary: RSA helpers for PyJWT
License: MIT
Author: Dmitry Orlov
Author-email: me@mosquito.su
Requires-Python: >=3.10,<4.0
Classifier: Intended Audience :: Developers
Classifier: License :: OSI Approved :: MIT License
Classifier: Natural Language :: Russian
Classifier: Operating System :: MacOS
Classifier: Operating System :: POSIX
Classifier: Programming Language :: Python
Classifier: Programming Language :: Python :: 3
Classifier: Programming Language :: Python :: 3.10
Classifier: Programming Language :: Python :: 3.11
Classifier: Programming Language :: Python :: 3.12
Classifier: Programming Language :: Python :: 3.13
Classifier: Programming Language :: Python :: Implementation :: CPython
Classifier: Topic :: Security
Classifier: Typing :: Typed
Requires-Dist: cryptography (>=45.0,<46.0)
Requires-Dist: pyjwt (>=2.10,<3.0)
